artd_service/__init__.py
artd_service/admin.py
artd_service/apps.py
artd_service/models.py
artd_service/signals.py
artd_service/tests.py
artd_service/views.py
artd_service/data/__init__.py
artd_service/data/service_data.py
artd_service/management/__init__.py
artd_service/management/commands/__init__.py
artd_service/management/commands/create_apps.py
artd_service/management/commands/create_services.py
artd_service/management/commands/insert_installed_apps_and_permissions.py
artd_service/migrations/0001_initial.py
artd_service/migrations/0002_installedapp.py
artd_service/migrations/0003_installedapp_created_at_installedapp_status_and_more.py
artd_service/migrations/0004_apppermission.py
artd_service/migrations/0005_apppermission_created_at_apppermission_status_and_more.py
artd_service/migrations/0006_serviceapps.py
artd_service/migrations/0007_alter_serviceapps_options.py
artd_service/migrations/__init__.py
service/__init__.py
service/asgi.py
service/settings.py
service/urls.py
service/wsgi.py
artd_service-1.0.8.dist-info/LICENSE
artd_service-1.0.8.dist-info/METADATA
artd_service-1.0.8.dist-info/WHEEL
artd_service-1.0.8.dist-info/top_level.txt
artd_service-1.0.8.dist-info/RECORD
